huaweicloudsdkecs/__init__.py
huaweicloudsdkecs/v2/__init__.py
huaweicloudsdkecs/v2/ecs_async_client.py
huaweicloudsdkecs/v2/ecs_client.py
huaweicloudsdkecs/v2/model/__init__.py
huaweicloudsdkecs/v2/model/accept_scheduled_event_request.py
huaweicloudsdkecs/v2/model/accept_scheduled_event_response.py
huaweicloudsdkecs/v2/model/add_server_group_member_request.py
huaweicloudsdkecs/v2/model/add_server_group_member_request_body.py
huaweicloudsdkecs/v2/model/add_server_group_member_response.py
huaweicloudsdkecs/v2/model/asic_accelerator_info.py
huaweicloudsdkecs/v2/model/associate_server_virtual_ip_option.py
huaweicloudsdkecs/v2/model/associate_server_virtual_ip_request.py
huaweicloudsdkecs/v2/model/associate_server_virtual_ip_request_body.py
huaweicloudsdkecs/v2/model/associate_server_virtual_ip_response.py
huaweicloudsdkecs/v2/model/association.py
huaweicloudsdkecs/v2/model/attach_server_volume_option.py
huaweicloudsdkecs/v2/model/attach_server_volume_request.py
huaweicloudsdkecs/v2/model/attach_server_volume_request_body.py
huaweicloudsdkecs/v2/model/attach_server_volume_response.py
huaweicloudsdkecs/v2/model/attachable_quantity_for_nic.py
huaweicloudsdkecs/v2/model/batch_add_server_group_member_req.py
huaweicloudsdkecs/v2/model/batch_add_server_group_member_request.py
huaweicloudsdkecs/v2/model/batch_add_server_group_member_response.py
huaweicloudsdkecs/v2/model/batch_add_server_nic_option.py
huaweicloudsdkecs/v2/model/batch_add_server_nics_request.py
huaweicloudsdkecs/v2/model/batch_add_server_nics_request_body.py
huaweicloudsdkecs/v2/model/batch_add_server_nics_response.py
huaweicloudsdkecs/v2/model/batch_add_server_tag.py
huaweicloudsdkecs/v2/model/batch_attach_sharable_volumes_option.py
huaweicloudsdkecs/v2/model/batch_attach_sharable_volumes_request.py
huaweicloudsdkecs/v2/model/batch_attach_sharable_volumes_request_body.py
huaweicloudsdkecs/v2/model/batch_attach_sharable_volumes_response.py
huaweicloudsdkecs/v2/model/batch_create_server_tags_request.py
huaweicloudsdkecs-3.1.184.dist-info/METADATA
huaweicloudsdkecs-3.1.184.dist-info/WHEEL
huaweicloudsdkecs-3.1.184.dist-info/licenses/LICENSE
huaweicloudsdkecs-3.1.184.dist-info/RECORD
